{
  "metadata": {
    "generated_at": "2026-05-07 07:46:04",
    "data_mode": "yfinance (no FMP API required)",
    "api_calls": {
      "api_calls_made": 31,
      "cache_entries": 55,
      "rate_limit_reached": false
    },
    "cli_inputs": {
      "breadth_200dma": 56.18,
      "breadth_200dma_source": "auto",
      "breadth_200dma_auto_date": "2026-05-05",
      "breadth_50dma": null,
      "put_call_ratio": null,
      "vix_term_structure": null,
      "margin_debt_yoy_pct": null
    },
    "vix_term_auto": {
      "vix": 17.39,
      "vix3m": 20.57,
      "ratio": 0.845,
      "classification": "steep_contango"
    },
    "index_data": {
      "sp500_price": 7365.1201171875,
      "sp500_year_high": 7369.22021484375,
      "sp500_distance_from_high_pct": -0.06,
      "qqq_price": 695.77001953125,
      "vix_level": 17.389999389648438
    }
  },
  "composite": {
    "composite_score": 27.2,
    "zone": "Yellow (Early Warning)",
    "zone_color": "yellow",
    "risk_budget": "80-90%",
    "guidance": "Early warning signs detected. Tighten stops and reduce new entries.",
    "actions": [
      "Tighten stop-losses by 10-20%",
      "Reduce new position sizes by 25-50%",
      "Review weakest positions for exits",
      "Monitor distribution days closely"
    ],
    "strongest_warning": {
      "component": "distribution_days",
      "label": "Distribution Day Count",
      "score": 75
    },
    "weakest_warning": {
      "component": "leading_stocks",
      "label": "Leading Stock Health",
      "score": 0
    },
    "data_quality": {
      "available_count": 6,
      "total_components": 6,
      "label": "Complete (6/6 components)",
      "missing_components": []
    },
    "correlation_adjustment": [],
    "component_scores": {
      "distribution_days": {
        "score": 75,
        "adjusted_score": 75,
        "weight": 0.25,
        "weighted_contribution": 18.8,
        "label": "Distribution Day Count"
      },
      "leading_stocks": {
        "score": 0,
        "adjusted_score": 0,
        "weight": 0.2,
        "weighted_contribution": 0.0,
        "label": "Leading Stock Health"
      },
      "defensive_rotation": {
        "score": 0,
        "adjusted_score": 0,
        "weight": 0.15,
        "weighted_contribution": 0.0,
        "label": "Defensive Sector Rotation"
      },
      "breadth_divergence": {
        "score": 40,
        "adjusted_score": 40,
        "weight": 0.15,
        "weighted_contribution": 6.0,
        "label": "Market Breadth Divergence"
      },
      "index_technical": {
        "score": 0,
        "adjusted_score": 0,
        "weight": 0.15,
        "weighted_contribution": 0.0,
        "label": "Index Technical Condition"
      },
      "sentiment": {
        "score": 25,
        "adjusted_score": 25,
        "weight": 0.1,
        "weighted_contribution": 2.5,
        "label": "Sentiment & Speculation"
      }
    }
  },
  "components": {
    "distribution_days": {
      "score": 75,
      "raw_score": 75,
      "effective_count": 4.5,
      "signal": "WARNING: O'Neil's threshold reached",
      "clustering": {
        "factor": 0.2,
        "recent_count": 1,
        "total_count": 5
      },
      "clustering_applied": false,
      "primary_index": "S&P 500",
      "sp500": {
        "distribution_days": 4,
        "stalling_days": 1,
        "effective_count": 4.5,
        "details": [
          {
            "date": "2026-05-04",
            "type": "distribution",
            "pct_change": -0.41,
            "volume_change": 7.6,
            "window_index": 2
          },
          {
            "date": "2026-04-28",
            "type": "distribution",
            "pct_change": -0.49,
            "volume_change": 2.4,
            "window_index": 6
          },
          {
            "date": "2026-04-23",
            "type": "distribution",
            "pct_change": -0.41,
            "volume_change": 7.9,
            "window_index": 9
          },
          {
            "date": "2026-04-21",
            "type": "distribution",
            "pct_change": -0.63,
            "volume_change": 10.7,
            "window_index": 11
          },
          {
            "date": "2026-04-07",
            "type": "stalling",
            "pct_change": 0.08,
            "volume_change": 16.6,
            "window_index": 21
          }
        ]
      },
      "nasdaq": {
        "distribution_days": 3,
        "stalling_days": 1,
        "effective_count": 3.5,
        "details": [
          {
            "date": "2026-04-28",
            "type": "distribution",
            "pct_change": -1.01,
            "volume_change": 4.4,
            "window_index": 6
          },
          {
            "date": "2026-04-23",
            "type": "distribution",
            "pct_change": -0.56,
            "volume_change": 7.3,
            "window_index": 9
          },
          {
            "date": "2026-04-21",
            "type": "distribution",
            "pct_change": -0.38,
            "volume_change": 6.6,
            "window_index": 11
          },
          {
            "date": "2026-04-07",
            "type": "stalling",
            "pct_change": 0.02,
            "volume_change": 42.3,
            "window_index": 21
          }
        ]
      }
    },
    "leading_stocks": {
      "score": 0,
      "signal": "HEALTHY: Leadership intact",
      "avg_deterioration": 0.0,
      "etfs_evaluated": 10,
      "etfs_deteriorating": 0,
      "deteriorating_pct": 0.0,
      "amplified": false,
      "etf_details": {
        "SOXQ": {
          "deterioration_score": 0,
          "price": 90.33000183105469,
          "year_high": 90.33999633789062,
          "distance_from_high_pct": -0.0,
          "flags": []
        },
        "SOXX": {
          "deterioration_score": 0,
          "price": 506.8699951171875,
          "year_high": 506.94000244140625,
          "distance_from_high_pct": -0.0,
          "flags": []
        },
        "PSI": {
          "deterioration_score": 0,
          "price": 144.61000061035156,
          "year_high": 144.6300048828125,
          "distance_from_high_pct": -0.0,
          "flags": []
        },
        "SMH": {
          "deterioration_score": 0,
          "price": 549.760009765625,
          "year_high": 549.8800048828125,
          "distance_from_high_pct": -0.0,
          "flags": []
        },
        "BOTZ": {
          "deterioration_score": 0,
          "price": 39.880001068115234,
          "year_high": 39.900001525878906,
          "distance_from_high_pct": -0.1,
          "flags": []
        },
        "ARKW": {
          "deterioration_score": 0,
          "price": 145.94000244140625,
          "year_high": 146.0850067138672,
          "distance_from_high_pct": -0.1,
          "flags": []
        },
        "KOMP": {
          "deterioration_score": 0,
          "price": 68.56999969482422,
          "year_high": 68.6500015258789,
          "distance_from_high_pct": -0.1,
          "flags": []
        },
        "ICLN": {
          "deterioration_score": 0,
          "price": 21.31999969482422,
          "year_high": 21.440000534057617,
          "distance_from_high_pct": -0.6,
          "flags": []
        },
        "CLOU": {
          "deterioration_score": 0,
          "price": 22.329999923706055,
          "year_high": 22.489999771118164,
          "distance_from_high_pct": -0.7,
          "flags": []
        },
        "BUG": {
          "deterioration_score": 0,
          "price": 27.969999313354492,
          "year_high": 28.219999313354492,
          "distance_from_high_pct": -0.9,
          "flags": []
        }
      },
      "data_available": true,
      "fetch_success_rate": 1.0,
      "partial_data_count": 0,
      "basket_mode": "dynamic",
      "basket": [
        "SOXQ",
        "SOXX",
        "PSI",
        "SMH",
        "BOTZ",
        "ARKW",
        "KOMP",
        "ICLN",
        "CLOU",
        "BUG"
      ]
    },
    "defensive_rotation": {
      "score": 0,
      "signal": "HEALTHY: Growth leading",
      "data_available": true,
      "relative_performance": -11.01,
      "defensive_avg_return": 0.5,
      "offensive_avg_return": 11.52,
      "defensive_details": {
        "XLU": -2.29,
        "XLP": 1.76,
        "XLV": -2.85,
        "VNQ": 5.4
      },
      "offensive_details": {
        "XLK": 20.0,
        "XLC": 3.11,
        "XLY": 8.17,
        "QQQ": 14.8
      },
      "lookback_days": 20,
      "fetch_success_rate": 1.0,
      "confirmation": "unconfirmed",
      "multi_period": {
        "10": {
          "lookback": 10,
          "defensive_avg": 1.63,
          "offensive_avg": 3.53,
          "relative": -1.9,
          "score": 1,
          "defensive_leading": false
        },
        "20": {
          "lookback": 20,
          "defensive_avg": 0.5,
          "offensive_avg": 11.52,
          "relative": -11.01,
          "score": 0,
          "defensive_leading": false
        },
        "40": {
          "lookback": 40,
          "defensive_avg": -0.54,
          "offensive_avg": 10.42,
          "relative": -10.96,
          "score": 0,
          "defensive_leading": false
        }
      }
    },
    "breadth_divergence": {
      "score": 40,
      "signal": "CAUTION: Mild breadth weakness",
      "data_available": true,
      "breadth_200dma": 56.18,
      "breadth_50dma": null,
      "index_near_highs": true,
      "index_distance_from_high_pct": -0.1,
      "divergence_detected": true,
      "breadth_source": "auto",
      "breadth_auto_date": "2026-05-05"
    },
    "index_technical": {
      "score": 0,
      "signal": "HEALTHY: Technical structure intact",
      "sp500": {
        "raw_score": 0,
        "price": 7365.12,
        "flags": [],
        "mas": {
          "ema21": 7083.33,
          "ema50": 6940.71,
          "sma200": 6743.07
        },
        "data_available": true
      },
      "nasdaq": {
        "raw_score": 0,
        "price": 695.77,
        "flags": [],
        "mas": {
          "ema21": 651.7,
          "ema50": 629.87,
          "sma200": 604.71
        },
        "data_available": true
      },
      "data_available": true
    },
    "sentiment": {
      "score": 25,
      "signal": "MIXED: Moderate sentiment",
      "data_available": true,
      "total_points": 25,
      "details": {
        "put_call_ratio": {
          "value": null,
          "points": 0,
          "interpretation": "No data"
        },
        "vix_level": {
          "value": 17.39,
          "points": 0,
          "interpretation": "Normal range"
        },
        "vix_term_structure": {
          "value": "steep_contango",
          "points": 25,
          "interpretation": "Market expects calm - complacency in term structure"
        }
      }
    }
  },
  "follow_through_day": {
    "ftd_detected": false,
    "applicable": false,
    "reason": "Composite < 40 (Green/Yellow zone) - FTD monitoring not needed"
  },
  "historical_comparison": {
    "closest_match": "2018 (Q4 Correction)",
    "closest_ssd": 1553.8,
    "comparisons": [
      {
        "name": "2018 (Q4 Correction)",
        "ssd": 1553.8,
        "scores": {
          "distribution_days": 60,
          "leading_stocks": 50,
          "defensive_rotation": 40,
          "breadth_divergence": 55,
          "index_technical": 65,
          "sentiment": 55
        }
      },
      {
        "name": "2022 (Rate Hike Bear)",
        "ssd": 3415.0,
        "scores": {
          "distribution_days": 75,
          "leading_stocks": 90,
          "defensive_rotation": 60,
          "breadth_divergence": 70,
          "index_technical": 80,
          "sentiment": 65
        }
      },
      {
        "name": "2007 (Financial Crisis)",
        "ssd": 3440.0,
        "scores": {
          "distribution_days": 80,
          "leading_stocks": 75,
          "defensive_rotation": 85,
          "breadth_divergence": 80,
          "index_technical": 70,
          "sentiment": 75
        }
      },
      {
        "name": "2000 (Dot-Com Bubble)",
        "ssd": 3652.5,
        "scores": {
          "distribution_days": 90,
          "leading_stocks": 85,
          "defensive_rotation": 70,
          "breadth_divergence": 95,
          "index_technical": 60,
          "sentiment": 90
        }
      }
    ],
    "narrative": "Closest to 2018 (Q4 Correction). Key differences: Distribution Days is 15pt higher than 2018 (Q4 Correction); Leading Stocks is 50pt lower than 2018 (Q4 Correction); Defensive Rotation is 40pt lower than 2018 (Q4 Correction); Breadth Divergence is 15pt lower than 2018 (Q4 Correction); Index Technical is 65pt lower than 2018 (Q4 Correction); Sentiment is 30pt lower than 2018 (Q4 Correction)."
  },
  "scenarios": [
    {
      "name": "Breadth Deterioration",
      "description": "Breadth divergence worsens to 55+",
      "changes": {
        "breadth_divergence": 55
      },
      "new_score": 29.5,
      "new_zone": "Yellow (Early Warning)",
      "delta": 2.3
    },
    {
      "name": "Distribution Reset",
      "description": "Distribution days ease to 55 or less",
      "changes": {
        "distribution_days": 55
      },
      "new_score": 22.2,
      "new_zone": "Yellow (Early Warning)",
      "delta": -5.0
    },
    {
      "name": "Full Deterioration",
      "description": "3 weakest components each worsen by +20pt",
      "changes": {
        "leading_stocks": 20,
        "defensive_rotation": 20,
        "index_technical": 20
      },
      "new_score": 37.2,
      "new_zone": "Yellow (Early Warning)",
      "delta": 10.0
    },
    {
      "name": "Recovery",
      "description": "2 strongest warning signals improve by -30pt",
      "changes": {
        "distribution_days": 45,
        "breadth_divergence": 10
      },
      "new_score": 15.2,
      "new_zone": "Green (Normal)",
      "delta": -12.0
    }
  ],
  "delta": {
    "components": {
      "distribution_days": {
        "delta": 0,
        "direction": "stable",
        "previous": 75
      },
      "leading_stocks": {
        "delta": -6,
        "direction": "improving",
        "previous": 6
      },
      "defensive_rotation": {
        "delta": -2,
        "direction": "stable",
        "previous": 2
      },
      "breadth_divergence": {
        "delta": 0,
        "direction": "stable",
        "previous": 40
      },
      "index_technical": {
        "delta": 0,
        "direction": "stable",
        "previous": 0
      },
      "sentiment": {
        "delta": 0,
        "direction": "stable",
        "previous": 25
      }
    },
    "composite_delta": -1.6,
    "composite_direction": "stable",
    "previous_date": "2026-05-06 21:06:18",
    "previous_composite": 28.8
  }
}